ansi_stdio/__init__.py
ansi_stdio/__main__.py
ansi_stdio/buffer/__init__.py
ansi_stdio/buffer/animation.py
ansi_stdio/buffer/buffer.py
ansi_stdio/buffer/frame.py
ansi_stdio/cli/__init__.py
ansi_stdio/cli/fonts.py
ansi_stdio/cli/quantize.py
ansi_stdio/core/__init__.py
ansi_stdio/core/box.py
ansi_stdio/core/clock.py
ansi_stdio/core/saved.py
ansi_stdio/core/versioned.py
ansi_stdio/loader/__init__.py
ansi_stdio/loader/ansi.py
ansi_stdio/loader/asciinema.py
ansi_stdio/terminal/__init__.py
ansi_stdio/terminal/capture.py
ansi_stdio/terminal/info.py
ansi_stdio/terminal/render.py
ansi_stdio/utils/__init__.py
ansi_stdio/utils/fonts.py
ansi_stdio-0.0.2.dist-info/entry_points.txt
ansi_stdio-0.0.2.dist-info/licenses/LICENSE.md
ansi_stdio-0.0.2.dist-info/WHEEL
ansi_stdio-0.0.2.dist-info/METADATA
ansi_stdio-0.0.2.dist-info/RECORD
