Metadata-Version: 2.4
Name: ansi_stdio
Version: 0.0.2
Summary: ANSI text animation library
Author-email: Gareth Davidson <gaz@bitplane.net>
Requires-Python: >=3.10
Classifier: Development Status :: 2 - Pre-Alpha
Classifier: Programming Language :: Python :: 3
Classifier: Programming Language :: Python :: 3.10
Classifier: Programming Language :: Python :: 3.11
Classifier: License :: Public Domain
Classifier: Operating System :: OS Independent
Classifier: Topic :: Software Development :: Libraries :: Python Modules
Classifier: Environment :: Console
Classifier: Intended Audience :: Developers
Classifier: Topic :: Terminals
License-File: LICENSE.md
Requires-Dist: rich
Requires-Dist: pyte
Requires-Dist: matplotlib
Requires-Dist: flake8 ; extra == "dev"
Requires-Dist: pre-commit ; extra == "dev"
Requires-Dist: pytest ; extra == "dev"
Requires-Dist: coverage ; extra == "dev"
Requires-Dist: pytest-cov ; extra == "dev"
Requires-Dist: pydoc-markdown ; extra == "dev"
Requires-Dist: build ; extra == "dev"
Requires-Dist: twine ; extra == "dev"
Project-URL: Bug Tracker, https://github.com/bitplane/ansi_stdio/issues
Project-URL: Homepage, https://github.com/bitplane/ansi_stdio
Project-URL: Source Code, https://github.com/bitplane/ansi_stdio
Provides-Extra: dev
